{"trial_id": "26", "hyperparameters": {"space": [{"class_name": "Int", "config": {"name": "n_layers", "default": null, "conditions": [], "min_value": 2, "max_value": 8, "step": 1, "sampling": "linear"}}, {"class_name": "Int", "config": {"name": "units_0", "default": null, "conditions": [], "min_value": 16, "max_value": 512, "step": 16, "sampling": "linear"}}, {"class_name": "Choice", "config": {"name": "activation_0", "default": "relu", "conditions": [], "values": ["relu", "tanh", "elu", "selu", "swish"], "ordered": false}}, {"class_name": "Boolean", "config": {"name": "batch_norm_0", "default": false, "conditions": []}}, {"class_name": "Float", "config": {"name": "dropout_0", "default": 0.0, "conditions": [], "min_value": 0.0, "max_value": 0.6, "step": 0.05, "sampling": "linear"}}, {"class_name": "Int", "config": {"name": "units_1", "default": null, "conditions": [], "min_value": 16, "max_value": 512, "step": 16, "sampling": "linear"}}, {"class_name": "Choice", "config": {"name": "activation_1", "default": "relu", "conditions": [], "values": ["relu", "tanh", "elu", "selu", "swish"], "ordered": false}}, {"class_name": "Boolean", "config": {"name": "batch_norm_1", "default": false, "conditions": []}}, {"class_name": "Float", "config": {"name": "dropout_1", "default": 0.0, "conditions": [], "min_value": 0.0, "max_value": 0.6, "step": 0.05, "sampling": "linear"}}, {"class_name": "Choice", "config": {"name": "learning_rate", "default": 0.05, "conditions": [], "values": [0.05, 0.01, 0.005, 0.001, 0.0005, 0.0001, 5e-05], "ordered": true}}, {"class_name": "Choice", "config": {"name": "optimizer", "default": "adam", "conditions": [], "values": ["adam", "adamw", "sgd", "rmsprop", "nadam"], "ordered": false}}, {"class_name": "Int", "config": {"name": "units_2", "default": null, "conditions": [], "min_value": 16, "max_value": 512, "step": 16, "sampling": "linear"}}, {"class_name": "Choice", "config": {"name": "activation_2", "default": "relu", "conditions": [], "values": ["relu", "tanh", "elu", "selu", "swish"], "ordered": false}}, {"class_name": "Boolean", "config": {"name": "batch_norm_2", "default": false, "conditions": []}}, {"class_name": "Float", "config": {"name": "dropout_2", "default": 0.0, "conditions": [], "min_value": 0.0, "max_value": 0.6, "step": 0.05, "sampling": "linear"}}, {"class_name": "Int", "config": {"name": "units_3", "default": null, "conditions": [], "min_value": 16, "max_value": 512, "step": 16, "sampling": "linear"}}, {"class_name": "Choice", "config": {"name": "activation_3", "default": "relu", "conditions": [], "values": ["relu", "tanh", "elu", "selu", "swish"], "ordered": false}}, {"class_name": "Boolean", "config": {"name": "batch_norm_3", "default": false, "conditions": []}}, {"class_name": "Float", "config": {"name": "dropout_3", "default": 0.0, "conditions": [], "min_value": 0.0, "max_value": 0.6, "step": 0.05, "sampling": "linear"}}, {"class_name": "Int", "config": {"name": "units_4", "default": null, "conditions": [], "min_value": 16, "max_value": 512, "step": 16, "sampling": "linear"}}, {"class_name": "Choice", "config": {"name": "activation_4", "default": "relu", "conditions": [], "values": ["relu", "tanh", "elu", "selu", "swish"], "ordered": false}}, {"class_name": "Boolean", "config": {"name": "batch_norm_4", "default": false, "conditions": []}}, {"class_name": "Float", "config": {"name": "dropout_4", "default": 0.0, "conditions": [], "min_value": 0.0, "max_value": 0.6, "step": 0.05, "sampling": "linear"}}, {"class_name": "Int", "config": {"name": "units_5", "default": null, "conditions": [], "min_value": 16, "max_value": 512, "step": 16, "sampling": "linear"}}, {"class_name": "Choice", "config": {"name": "activation_5", "default": "relu", "conditions": [], "values": ["relu", "tanh", "elu", "selu", "swish"], "ordered": false}}, {"class_name": "Boolean", "config": {"name": "batch_norm_5", "default": false, "conditions": []}}, {"class_name": "Float", "config": {"name": "dropout_5", "default": 0.0, "conditions": [], "min_value": 0.0, "max_value": 0.6, "step": 0.05, "sampling": "linear"}}, {"class_name": "Int", "config": {"name": "units_6", "default": null, "conditions": [], "min_value": 16, "max_value": 512, "step": 16, "sampling": "linear"}}, {"class_name": "Choice", "config": {"name": "activation_6", "default": "relu", "conditions": [], "values": ["relu", "tanh", "elu", "selu", "swish"], "ordered": false}}, {"class_name": "Boolean", "config": {"name": "batch_norm_6", "default": false, "conditions": []}}, {"class_name": "Float", "config": {"name": "dropout_6", "default": 0.0, "conditions": [], "min_value": 0.0, "max_value": 0.6, "step": 0.05, "sampling": "linear"}}, {"class_name": "Int", "config": {"name": "units_7", "default": null, "conditions": [], "min_value": 16, "max_value": 512, "step": 16, "sampling": "linear"}}, {"class_name": "Choice", "config": {"name": "activation_7", "default": "relu", "conditions": [], "values": ["relu", "tanh", "elu", "selu", "swish"], "ordered": false}}, {"class_name": "Boolean", "config": {"name": "batch_norm_7", "default": false, "conditions": []}}, {"class_name": "Float", "config": {"name": "dropout_7", "default": 0.0, "conditions": [], "min_value": 0.0, "max_value": 0.6, "step": 0.05, "sampling": "linear"}}, {"class_name": "Float", "config": {"name": "sgd_momentum", "default": 0.8, "conditions": [], "min_value": 0.8, "max_value": 0.99, "step": 0.01, "sampling": "linear"}}], "values": {"n_layers": 3, "units_0": 400, "activation_0": "relu", "batch_norm_0": false, "dropout_0": 0.5, "units_1": 416, "activation_1": "elu", "batch_norm_1": false, "dropout_1": 0.0, "learning_rate": 0.005, "optimizer": "adam", "units_2": 96, "activation_2": "selu", "batch_norm_2": true, "dropout_2": 0.55, "units_3": 16, "activation_3": "elu", "batch_norm_3": false, "dropout_3": 0.45, "units_4": 400, "activation_4": "selu", "batch_norm_4": true, "dropout_4": 0.35000000000000003, "units_5": 320, "activation_5": "selu", "batch_norm_5": true, "dropout_5": 0.35000000000000003, "units_6": 208, "activation_6": "elu", "batch_norm_6": true, "dropout_6": 0.35000000000000003, "units_7": 256, "activation_7": "selu", "batch_norm_7": true, "dropout_7": 0.35000000000000003, "sgd_momentum": 0.89}}, "metrics": {"metrics": {"accuracy": {"direction": "max", "observations": [{"value": [0.8498163223266602], "step": 18}]}, "auc": {"direction": "max", "observations": [{"value": [0.9293776750564575], "step": 18}]}, "f2_score": {"direction": "min", "observations": [{"value": [0.8670431971549988], "step": 18}]}, "loss": {"direction": "min", "observations": [{"value": [0.33187565207481384], "step": 18}]}, "precision": {"direction": "max", "observations": [{"value": [0.8286005556583405], "step": 18}]}, "recall": {"direction": "max", "observations": [{"value": [0.877218097448349], "step": 18}]}, "val_accuracy": {"direction": "max", "observations": [{"value": [0.7971751391887665], "step": 18}]}, "val_auc": {"direction": "max", "observations": [{"value": [0.8509665131568909], "step": 18}]}, "val_f2_score": {"direction": "max", "observations": [{"value": [0.8210119009017944], "step": 18}]}, "val_loss": {"direction": "min", "observations": [{"value": [0.5586698651313782], "step": 18}]}, "val_precision": {"direction": "max", "observations": [{"value": [0.7701865434646606], "step": 18}]}, "val_recall": {"direction": "max", "observations": [{"value": [0.8348729908466339], "step": 18}]}, "learning_rate": {"direction": "min", "observations": [{"value": [0.0018749999580904841], "step": 18}]}}}, "score": 0.8210119009017944, "best_step": 18, "status": "COMPLETED", "message": null}